{
  "id": "hsbc-live-plus",
  "name": "HSBC Live+",
  "issuer": "HSBC UAE",
  "network": "Visa",
  "annual_fee_aed": 314,
  "fee_waiver": {
    "condition": "min_annual_spend_aed",
    "value": 12000
  },
  "fx_fee_rate": 0.0275,
  "monthly_cashback_cap_aed": null,
  "cashback_rules": [
    {
      "category": "dining",
      "rate": 0.06,
      "monthly_cap_aed": 200,
      "min_monthly_spend_aed": 3000
    },
    {
      "category": "fuel",
      "rate": 0.05,
      "monthly_cap_aed": 200,
      "min_monthly_spend_aed": 3000
    },
    {
      "category": "groceries",
      "rate": 0.02,
      "monthly_cap_aed": 200,
      "min_monthly_spend_aed": 3000
    },
    {
      "category": "online",
      "rate": 0.02,
      "monthly_cap_aed": 200,
      "min_monthly_spend_aed": 3000
    },
    {
      "category": "other",
      "rate": 0.005,
      "monthly_cap_aed": null,
      "min_monthly_spend_aed": 3000
    }
  ],
  "source_url": "https://www.hsbc.ae/credit-cards/products/live-plus/",
  "last_verified": "2026-03-11",
  "notes": "Annual fee AED 314 waived if annual spend ≥ AED 12,000. Min monthly spend AED 3,000 required. 6% dining, 5% fuel, 2% groceries & online (entertainment), each capped AED 200/mo."
}
